metamodule.py
metamodule-1.1.dist-info/DESCRIPTION.rst
metamodule-1.1.dist-info/METADATA
metamodule-1.1.dist-info/RECORD
metamodule-1.1.dist-info/WHEEL
metamodule-1.1.dist-info/metadata.json
metamodule-1.1.dist-info/top_level.txt
