Metadata-Version: 2.0
Name: metamodule
Version: 1.1
Summary: A tiny Python module for taking control of your library's public API.
Home-page: https://github.com/njsmith/metamodule
Author: Nathaniel J. Smith
Author-email: njs@pobox.com
License: 2-clause BSD
Platform: UNKNOWN
Classifier: Development Status :: 4 - Beta
Classifier: Intended Audience :: Developers
Classifier: License :: OSI Approved :: BSD License
Classifier: Programming Language :: Python :: 2
Classifier: Programming Language :: Python :: 2.6
Classifier: Programming Language :: Python :: 2.7
Classifier: Programming Language :: Python :: 3
Classifier: Programming Language :: Python :: 3.2
Classifier: Programming Language :: Python :: 3.3
Classifier: Programming Language :: Python :: 3.4
Classifier: Programming Language :: Python :: 3.5
